cli_passwords/__init__.py
cli_passwords/cli_passwords.py
cli_passwords-0.1.2.dist-info/DESCRIPTION.rst
cli_passwords-0.1.2.dist-info/METADATA
cli_passwords-0.1.2.dist-info/RECORD
cli_passwords-0.1.2.dist-info/WHEEL
cli_passwords-0.1.2.dist-info/metadata.json
cli_passwords-0.1.2.dist-info/top_level.txt
