Metadata-Version: 2.0
Name: cli-passwords
Version: 0.1.2
Summary: Makes securely getting, storing, and retrying passwords from a command line interface easy!
Home-page: https://github.com/timmartin19/cli_passwords
Author: Tim Martin
Author-email: tim@timmartin.me
License: MIT license
Keywords: cli-passwords command line interface cli password retrieval keyring storage secure
Platform: UNKNOWN
Classifier: Development Status :: 2 - Pre-Alpha
Classifier: Intended Audience :: Developers
Classifier: License :: OSI Approved :: MIT License
Classifier: Natural Language :: English
Classifier: Programming Language :: Python :: 2
Classifier: Programming Language :: Python :: 2.6
Classifier: Programming Language :: Python :: 2.7
Classifier: Programming Language :: Python :: 3
Classifier: Programming Language :: Python :: 3.3
Classifier: Programming Language :: Python :: 3.4
Classifier: Programming Language :: Python :: 3.5
Requires-Dist: Click (>=6.0)
Requires-Dist: keyring
